Workbook

Sheet Dizionario campi
A1: Codice campo | B1: Campo | C1: Fonte
A2: D1 | B2: Issue Key | C2: J2
A3: D2 | B3: Full name | C3: J2
A4: D3 | B4: Period | C4: J2
A5: D4 | B5: Account Key | C5: J2
A6: D5 | B6: Account Name | C6: J2
A7: D6 | B7: Account Status | C7: J2
A8: D7 | B8: Account Category | C8: J2
A9: D8 | B9: Issue summary | C9: J2
A10: D9 | B10: Ore principali | C10: J2
A11: D10 | B11: Cliente | C11: J2
A12: D11 | B12: Category Key | C12: T4
... A71: D70 | B71: Tipo commessa | C71: T9

Sheet P1O1-A Mensile Actual
A1: Codice campo | B1: Campo | C1: Tipo | D1: Fonte
A2: D1 | B2: Issue Key | C2: Input | D2: J2
A3: D2 | B3: Full name | C3: Input | D3: J2
A4: D3 | B4: Period | C4: Input | D4: J2
A5: D4 | B5: Account Key | C5: Input | D5: J2
A6: D5 | B6: Account Name | C6: Input | D6: J2
A7: D6 | B7: Account Status | C7: Input | D7: J2
A8: D7 | B8: Account Category | C8: Input | D8: J2
A9: D8 | B9: Issue summary | C9: Input | D9: J2
A10: D9 | B10: Ore principali | C10: Input | D10: J2
A11: D10 | B11: Cliente | C11: Input | D11: J2
A12: D11 | B12: Category Key | C12: Output | D12: T4
... A37: D36 | B37: Gruppo cliente | C37: Output | D37: T6

Sheet P2O1-A Inframensile Actual
A1: Codice campo | B1: Campo | C1: Tipo | D1: Fonte
A2: =+INDEX('Dizionario campi'!A:A,MATCH(B2,'Dizionario campi'!B:B,0),1) -> D1 | B2: Issue Key | C2: Input | D2: =+INDEX('Dizionario campi'!C:C,MATCH(B2,'Dizionario campi'!B:B,0),1) -> J2
A3: =+INDEX('Dizionario campi'!A:A,MATCH(B3,'Dizionario campi'!B:B,0),1) -> D9 | B3: Ore principali | C3: Input | D3: =+INDEX('Dizionario campi'!C:C,MATCH(B3,'Dizionario campi'!B:B,0),1) -> J2
A4: =+INDEX('Dizionario campi'!A:A,MATCH(B4,'Dizionario campi'!B:B,0),1) -> D37 | B4: Work date | C4: Input | D4: =+INDEX('Dizionario campi'!C:C,MATCH(B4,'Dizionario campi'!B:B,0),1) -> J2
A5: =+INDEX('Dizionario campi'!A:A,MATCH(B5,'Dizionario campi'!B:B,0),1) -> D2 | B5: Full name | C5: Input | D5: =+INDEX('Dizionario campi'!C:C,MATCH(B5,'Dizionario campi'!B:B,0),1) -> J2
A6: =+INDEX('Dizionario campi'!A:A,MATCH(B6,'Dizionario campi'!B:B,0),1) -> D3 | B6: Period | C6: Input | D6: =+INDEX('Dizionario campi'!C:C,MATCH(B6,'Dizionario campi'!B:B,0),1) -> J2
A7: =+INDEX('Dizionario campi'!A:A,MATCH(B7,'Dizionario campi'!B:B,0),1) -> D4 | B7: Account Key | C7: Input | D7: =+INDEX('Dizionario campi'!C:C,MATCH(B7,'Dizionario campi'!B:B,0),1) -> J2
A8: =+INDEX('Dizionario campi'!A:A,MATCH(B8,'Dizionario campi'!B:B,0),1) -> D5 | B8: Account Name | C8: Input | D8: =+INDEX('Dizionario campi'!C:C,MATCH(B8,'Dizionario campi'!B:B,0),1) -> J2
A9: =+INDEX('Dizionario campi'!A:A,MATCH(B9,'Dizionario campi'!B:B,0),1) -> D7 | B9: Account Category | C9: Input | D9: =+INDEX('Dizionario campi'!C:C,MATCH(B9,'Dizionario campi'!B:B,0),1) -> J2
A10: =+INDEX('Dizionario campi'!A:A,MATCH(B10,'Dizionario campi'!B:B,0),1) -> D38 | B10: Work Description | C10: Input | D10: =+INDEX('Dizionario campi'!C:C,MATCH(B10,'Dizionario campi'!B:B,0),1) -> J2
A11: =+INDEX('Dizionario campi'!A:A,MATCH(B11,'Dizionario campi'!B:B,0),1) -> D32 | B11: Team risorsa new | C11: Input | D11: =+INDEX('Dizionario campi'!C:C,MATCH(B11,'Dizionario campi'!B:B,0),1) -> O1
A12: =+INDEX('Dizionario campi'!A:A,MATCH(B12,'Dizionario campi'!B:B,0),1) -> D33 | B12: Area risorsa new | C12: Output | D12: =+INDEX('Dizionario campi'!C:C,MATCH(B12,'Dizionario campi'!B:B,0),1) -> T5

Sheet P3O2-Linked issue Actual
A1: Codice campo | B1: Campo | C1: Tipo | D1: Fonte
A2: =+INDEX('Dizionario campi'!A:A,MATCH(B2,'Dizionario campi'!B:B,0),1) -> D1 | B2: Issue key | C2: Input | D2: =+INDEX('Dizionario campi'!C:C,MATCH(B2,'Dizionario campi'!B:B,0),1) -> J2
A3: =+INDEX('Dizionario campi'!A:A,MATCH(B3,'Dizionario campi'!B:B,0),1) -> D39 | B3: Issue padre | C3: Output | D3: =+INDEX('Dizionario campi'!C:C,MATCH(B3,'Dizionario campi'!B:B,0),1) -> T7
A4: =+INDEX('Dizionario campi'!A:A,MATCH(B4,'Dizionario campi'!B:B,0),1) -> D40 | B4: Account issue key | C4: Output | D4: =+INDEX('Dizionario campi'!C:C,MATCH(B4,'Dizionario campi'!B:B,0),1) -> J3
A5: =+INDEX('Dizionario campi'!A:A,MATCH(B5,'Dizionario campi'!B:B,0),1) -> D41 | B5: Account issue padre | C5: Output | D5: =+INDEX('Dizionario campi'!C:C,MATCH(B5,'Dizionario campi'!B:B,0),1) -> J3
A6: =+INDEX('Dizionario campi'!A:A,MATCH(B6,'Dizionario campi'!B:B,0),1) -> D42 | B6: Account Category PADRE | C6: Output | D6: =+INDEX('Dizionario campi'!C:C,MATCH(B6,'Dizionario campi'!B:B,0),1) -> J3
A7: =+INDEX('Dizionario campi'!A:A,MATCH(B7,'Dizionario campi'!B:B,0),1) -> D43 | B7: Specifica T&M PADRE | C7: Output | D7: =+INDEX('Dizionario campi'!C:C,MATCH(B7,'Dizionario campi'!B:B,0),1) -> T11
A8: =+INDEX('Dizionario campi'!A:A,MATCH(B8,'Dizionario campi'!B:B,0),1) -> D44 | B8: Account Category FIGLIO | C8: Output | D8: =+INDEX('Dizionario campi'!C:C,MATCH(B8,'Dizionario campi'!B:B,0),1) -> T11
A9: =+INDEX('Dizionario campi'!A:A,MATCH(B9,'Dizionario campi'!B:B,0),1) -> D45 | B9: Specifica T&M FIGLIO | C9: Output | D9: =+INDEX('Dizionario campi'!C:C,MATCH(B9,'Dizionario campi'!B:B,0),1) -> T11
A10: =+INDEX('Dizionario campi'!A:A,MATCH(B10,'Dizionario campi'!B:B,0),1) -> D9 | B10: Ore principali | C10: Input | D10: =+INDEX('Dizionario campi'!C:C,MATCH(B10,'Dizionario campi'!B:B,0),1) -> J2
A11: =+INDEX('Dizionario campi'!A:A,MATCH(B11,'Dizionario campi'!B:B,0),1) -> D46 | B11: Ore secondarie | C11: Output | D11: =+INDEX('Dizionario campi'!C:C,MATCH(B11,'Dizionario campi'!B:B,0),1) -> J2

Sheet P4O3-Economics plus Actual
A1: Codice campo | B1: Campo | C1: Tipo | D1: Fonte
A2: =+INDEX('Dizionario campi'!A:A,MATCH(B2,'Dizionario campi'!B:B,0),1) -> D3 | B2: Period | C2: Output | D2: T13
A3: =+INDEX('Dizionario campi'!A:A,MATCH(B3,'Dizionario campi'!B:B,0),1) -> D28 | B3: Trimestre | C3: Output | D3: =+INDEX('Dizionario campi'!C:C,MATCH(B3,'Dizionario campi'!B:B,0),1) -> T13
A4: =+INDEX('Dizionario campi'!A:A,MATCH(B4,'Dizionario campi'!B:B,0),1) -> D29 | B4: Anno | C4: Output | D4: =+INDEX('Dizionario campi'!C:C,MATCH(B4,'Dizionario campi'!B:B,0),1) -> T13
A5: =+INDEX('Dizionario campi'!A:A,MATCH(B5,'Dizionario campi'!B:B,0),1) -> D56 | B5: WBS Profit center | C5: Output | D5: =+INDEX('Dizionario campi'!C:C,MATCH(B5,'Dizionario campi'!B:B,0),1) -> S1
A6: =+INDEX('Dizionario campi'!A:A,MATCH(B6,'Dizionario campi'!B:B,0),1) -> D10 | B6: Cliente | C6: Input | D6: =+INDEX('Dizionario campi'!C:C,MATCH(B6,'Dizionario campi'!B:B,0),1) -> J2
A7: =+INDEX('Dizionario campi'!A:A,MATCH(B7,'Dizionario campi'!B:B,0),1) -> D70 | B7: Tipo commessa | C7: Output | D7: =+INDEX('Dizionario campi'!C:C,MATCH(B7,'Dizionario campi'!B:B,0),1) -> T9
A8: =+INDEX('Dizionario campi'!A:A,MATCH(B8,'Dizionario campi'!B:B,0),1) -> D19 | B8: WBS Priority | C8: Input | D8: =+INDEX('Dizionario campi'!C:C,MATCH(B8,'Dizionario campi'!B:B,0),1) -> S1
A9: =+INDEX('Dizionario campi'!A:A,MATCH(B9,'Dizionario campi'!B:B,0),1) -> D16 | B9: WBS | C9: Input | D9: S1
A10: =+INDEX('Dizionario campi'!A:A,MATCH(B10,'Dizionario campi'!B:B,0),1) -> D18 | B10: WBS Descrizione | C10: Input | D10: =+INDEX('Dizionario campi'!C:C,MATCH(B10,'Dizionario campi'!B:B,0),1) -> S1
A11: =+INDEX('Dizionario campi'!A:A,MATCH(B11,'Dizionario campi'!B:B,0),1) -> D47 | B11: Ricavi | C11: Input | D11: =+INDEX('Dizionario campi'!C:C,MATCH(B11,'Dizionario campi'!B:B,0),1) -> S2
A12: =+INDEX('Dizionario campi'!A:A,MATCH(B12,'Dizionario campi'!B:B,0),1) -> D48 | B12: Costi | C12: Input | D12: =+INDEX('Dizionario campi'!C:C,MATCH(B12,'Dizionario campi'!B:B,0),1) -> S3
A13: =+INDEX('Dizionario campi'!A:A,MATCH(B13,'Dizionario campi'!B:B,0),1) -> D49 | B13: Margine | C13: Output | D13: =+INDEX('Dizionario campi'!C:C,MATCH(B13,'Dizionario campi'!B:B,0),1) -> P4O3
A14: =+INDEX('Dizionario campi'!A:A,MATCH(B14,'Dizionario campi'!B:B,0),1) -> D50 | B14: Fatturato | C14: Input | D14: =+INDEX('Dizionario campi'!C:C,MATCH(B14,'Dizionario campi'!B:B,0),1) -> S4
A15: =+INDEX('Dizionario campi'!A:A,MATCH(B15,'Dizionario campi'!B:B,0),1) -> D51 | B15: WBS Interna / Cliente | C15: Output | D15: =+INDEX('Dizionario campi'!C:C,MATCH(B15,'Dizionario campi'!B:B,0),1) -> T10
A16: =+INDEX('Dizionario campi'!A:A,MATCH(B16,'Dizionario campi'!B:B,0),1) -> D52 | B16: Attività specifica WBS | C16: Output | D16: =+INDEX('Dizionario campi'!C:C,MATCH(B16,'Dizionario campi'!B:B,0),1) -> T11
A17: =+INDEX('Dizionario campi'!A:A,MATCH(B17,'Dizionario campi'!B:B,0),1) -> D53 | B17: Costi Struttura | C17: Output | D17: =+INDEX('Dizionario campi'!C:C,MATCH(B17,'Dizionario campi'!B:B,0),1) -> P4O3
A18: =+INDEX('Dizionario campi'!A:A,MATCH(B18,'Dizionario campi'!B:B,0),1) -> D54 | B18: Ebitda Lob | C18: Output | D18: =+INDEX('Dizionario campi'!C:C,MATCH(B18,'Dizionario campi'!B:B,0),1) -> P4O3
A19: =+INDEX('Dizionario campi'!A:A,MATCH(B19,'Dizionario campi'!B:B,0),1) -> D55 | B19: Ebitda | C19: Output | D19: =+INDEX('Dizionario campi'!C:C,MATCH(B19,'Dizionario campi'!B:B,0),1) -> P4O3
A20: =+INDEX('Dizionario campi'!A:A,MATCH(B20,'Dizionario campi'!B:B,0),1) -> D17 | B20: PM commessa | C20: Output | D20: =+INDEX('Dizionario campi'!C:C,MATCH(B20,'Dizionario campi'!B:B,0),1) -> S1
A21: =+INDEX('Dizionario campi'!A:A,MATCH(B21,'Dizionario campi'!B:B,0),1) -> D36 | B21: Gruppo cliente | C21: Output | D21: =+INDEX('Dizionario campi'!C:C,MATCH(B21,'Dizionario campi'!B:B,0),1) -> T6
... A23: =+INDEX('Dizionario campi'!A:A,MATCH(B23,'Dizionario campi'!B:B,0),1) -> D35 | B23: Area commessa new | C23: Output | D23: =+INDEX('Dizionario campi'!C:C,MATCH(B23,'Dizionario campi'!B:B,0),1) -> T5

Sheet P5O4-Ore SAP x integr Actual
A1: Codice campo | B1: Campo | C1: Tipo | D1: Fonte
A2: =+INDEX('Dizionario campi'!A:A,MATCH(B2,'Dizionario campi'!B:B,0),1) -> D3 | B2: Period | C2: Input | D2: C2
A3: =+INDEX('Dizionario campi'!A:A,MATCH(B3,'Dizionario campi'!B:B,0),1) -> D16 | B3: WBS | C3: Input | D3: C2
A4: =+INDEX('Dizionario campi'!A:A,MATCH(B4,'Dizionario campi'!B:B,0),1) -> D18 | B4: WBS Descrizione | C4: Input | D4: =+INDEX('Dizionario campi'!C:C,MATCH(B4,'Dizionario campi'!B:B,0),1) -> S1
A5: =+INDEX('Dizionario campi'!A:A,MATCH(B5,'Dizionario campi'!B:B,0),1) -> D19 | B5: WBS Priority | C5: Input | D5: =+INDEX('Dizionario campi'!C:C,MATCH(B5,'Dizionario campi'!B:B,0),1) -> S1
A6: =+INDEX('Dizionario campi'!A:A,MATCH(B6,'Dizionario campi'!B:B,0),1) -> D57 | B6: Ore SAP | C6: Input | D6: =+INDEX('Dizionario campi'!C:C,MATCH(B6,'Dizionario campi'!B:B,0),1) -> C2

Sheet P6O5-Storico forecast completo
A1: Codice campo | B1: Campo | C1: Tipo | D1: Fonte
A2: =+INDEX('Dizionario campi'!A:A,MATCH(B2,'Dizionario campi'!B:B,0),1) -> D58 | B2: Data estrazione | C2: Output | D2: =+INDEX('Dizionario campi'!C:C,MATCH(B2,'Dizionario campi'!B:B,0),1) -> C3 / F1 / R1
A3: =+INDEX('Dizionario campi'!A:A,MATCH(B3,'Dizionario campi'!B:B,0),1) -> D59 | B3: Versione | C3: Output | D3: =+INDEX('Dizionario campi'!C:C,MATCH(B3,'Dizionario campi'!B:B,0),1) -> C3 / F1 / R1
A4: =+INDEX('Dizionario campi'!A:A,MATCH(B4,'Dizionario campi'!B:B,0),1) -> D60 | B4: Stato iniziativa | C4: Input | D4: =+INDEX('Dizionario campi'!C:C,MATCH(B4,'Dizionario campi'!B:B,0),1) -> C3 / F1 / R1
A5: =+INDEX('Dizionario campi'!A:A,MATCH(B5,'Dizionario campi'!B:B,0),1) -> D10 | B5: Cliente | C5: Input | D5: =+INDEX('Dizionario campi'!C:C,MATCH(B5,'Dizionario campi'!B:B,0),1) -> J2
A6: =+INDEX('Dizionario campi'!A:A,MATCH(B6,'Dizionario campi'!B:B,0),1) -> D16 | B6: WBS | C6: Input | D6: S1
A7: =+INDEX('Dizionario campi'!A:A,MATCH(B7,'Dizionario campi'!B:B,0),1) -> D18 | B7: WBS Descrizione | C7: Input | D7: =+INDEX('Dizionario campi'!C:C,MATCH(B7,'Dizionario campi'!B:B,0),1) -> S1
A8: =+INDEX('Dizionario campi'!A:A,MATCH(B8,'Dizionario campi'!B:B,0),1) -> D19 | B8: WBS Priority | C8: Input | D8: =+INDEX('Dizionario campi'!C:C,MATCH(B8,'Dizionario campi'!B:B,0),1) -> S1
A9: =+INDEX('Dizionario campi'!A:A,MATCH(B9,'Dizionario campi'!B:B,0),1) -> D51 | B9: WBS Interna / Cliente | C9: Output | D9: =+INDEX('Dizionario campi'!C:C,MATCH(B9,'Dizionario campi'!B:B,0),1) -> T10
A10: =+INDEX('Dizionario campi'!A:A,MATCH(B10,'Dizionario campi'!B:B,0),1) -> D61 | B10: Probabilità di successo | C10: Input | D10: =+INDEX('Dizionario campi'!C:C,MATCH(B10,'Dizionario campi'!B:B,0),1) -> C3 / F1 / R1
A11: =+INDEX('Dizionario campi'!A:A,MATCH(B11,'Dizionario campi'!B:B,0),1) -> D62 | B11: Probabilità alta / bassa | C11: Output | D11: =+INDEX('Dizionario campi'!C:C,MATCH(B11,'Dizionario campi'!B:B,0),1) -> T12
A12: =+INDEX('Dizionario campi'!A:A,MATCH(B12,'Dizionario campi'!B:B,0),1) -> D63 | B12: Linea Di Offerta | C12: Input | D12: =+INDEX('Dizionario campi'!C:C,MATCH(B12,'Dizionario campi'!B:B,0),1) -> C3 / F1 / R1
A13: =+INDEX('Dizionario campi'!A:A,MATCH(B13,'Dizionario campi'!B:B,0),1) -> D64 | B13: Perimetro | C13: Input | D13: =+INDEX('Dizionario campi'!C:C,MATCH(B13,'Dizionario campi'!B:B,0),1) -> C3 / F1 / R1
A14: =+INDEX('Dizionario campi'!A:A,MATCH(B14,'Dizionario campi'!B:B,0),1) -> D65 | B14: Ricavi netti | C14: Output | D14: =+INDEX('Dizionario campi'!C:C,MATCH(B14,'Dizionario campi'!B:B,0),1) -> C3 / F1 / R1
A15: =+INDEX('Dizionario campi'!A:A,MATCH(B15,'Dizionario campi'!B:B,0),1) -> D66 | B15: Ricavi lordi | C15: Input | D15: =+INDEX('Dizionario campi'!C:C,MATCH(B15,'Dizionario campi'!B:B,0),1) -> C3 / F1 / R1
A16: =+INDEX('Dizionario campi'!A:A,MATCH(B16,'Dizionario campi'!B:B,0),1) -> D29 | B16: Anno | C16: Output | D16: =+INDEX('Dizionario campi'!C:C,MATCH(B16,'Dizionario campi'!B:B,0),1) -> T13
A17: =+INDEX('Dizionario campi'!A:A,MATCH(B17,'Dizionario campi'!B:B,0),1) -> D28 | B17: Trimestre | C17: Output | D17: =+INDEX('Dizionario campi'!C:C,MATCH(B17,'Dizionario campi'!B:B,0),1) -> T13
A18: =+INDEX('Dizionario campi'!A:A,MATCH(B18,'Dizionario campi'!B:B,0),1) -> D67 | B18: Anno+trim | C18: Output | D18: =+INDEX('Dizionario campi'!C:C,MATCH(B18,'Dizionario campi'!B:B,0),1) -> T13
A19: =+INDEX('Dizionario campi'!A:A,MATCH(B19,'Dizionario campi'!B:B,0),1) -> D3 | B19: Period | C19: Output | D19: T13
A20: =+INDEX('Dizionario campi'!A:A,MATCH(B20,'Dizionario campi'!B:B,0),1) -> D68 | B20: Mese | C20: Output | D20: =+INDEX('Dizionario campi'!C:C,MATCH(B20,'Dizionario campi'!B:B,0),1) -> T13
A21: =+INDEX('Dizionario campi'!A:A,MATCH(B21,'Dizionario campi'!B:B,0),1) -> D34 | B21: Team commessa new | C21: Output | D21: =+INDEX('Dizionario campi'!C:C,MATCH(B21,'Dizionario campi'!B:B,0),1) -> T5
A22: =+INDEX('Dizionario campi'!A:A,MATCH(B22,'Dizionario campi'!B:B,0),1) -> D35 | B22: Area commessa new | C22: Output | D22: =+INDEX('Dizionario campi'!C:C,MATCH(B22,'Dizionario campi'!B:B,0),1) -> T5
A23: =+INDEX('Dizionario campi'!A:A,MATCH(B23,'Dizionario campi'!B:B,0),1) -> D36 | B23: Gruppo cliente | C23: Output | D23: =+INDEX('Dizionario campi'!C:C,MATCH(B23,'Dizionario campi'!B:B,0),1) -> T6
A24: =+INDEX('Dizionario campi'!A:A,MATCH(B24,'Dizionario campi'!B:B,0),1) -> D69 | B24: Tipo controparte | C24: Input | D24: =+INDEX('Dizionario campi'!C:C,MATCH(B24,'Dizionario campi'!B:B,0),1) -> F1
