Workbook
Name Actual: (PeriodInActual*(#REF!>0))*PeriodInPlan
Name ActualBeyond: PeriodInActual*(#REF!>0)
Name PercentComplete: PercentCompleteBeyond*PeriodInPlan
Name PercentCompleteBeyond: (#REF!=MEDIAN(#REF!,#REF!,#REF!+#REF!)*(#REF!>0))*((#REF!<(INT(#REF!+#REF!*#REF!)))+(#REF!=#REF!))*(#REF!>0)
Name period_selected: #REF!
Name PeriodInActual: #REF!=MEDIAN(#REF!,#REF!,#REF!+#REF!-1)
Name PeriodInPlan: #REF!=MEDIAN(#REF!,#REF!,#REF!+#REF!-1)
Name Plan: PeriodInPlan*(#REF!>0)

Sheet 01_Milestone_Deliverables
A1: Release | B1: Description | C1: Due Date
A2: AS-IS validato | B2: Assessment AS-IS completato: fonti, flussi, gap e pain point condivisi con business
A3: TO-BE approvato | B3: Blueprint target approvato: modello dati, regole, controlli, sicurezza e ownership
A4: Normalizzazione validata | B4: Dataset normalizzato e gestione scarti validati con utenti CDG
A5: Quadrature OK | B5: Elaborazioni, ribaltamenti, audit trail e quadrature approvati
A6: Output validati | B6: Dashboard CDG, dashboard tecnica e notifiche pronte per UAT
A7: Go-live approvato | B7: UAT e parallel run completati, cut-over formalizzato
A8: Go-live | B8: Sistema in esercizio con runbook, formazione e supporto primo ciclo di chiusura
A9: Evolutive opzionali | B9: Porting HR, AI anomaly detection e automazioni avanzate da pianificare post stabilizzazione

Sheet 02_Dependencies
A1: ID | B1: Activity | C1: Owner | D1: Release | E1: Status | F1: Due Date (old) | G1: Due Date (new) | H1: Linked Tasks
A2: D1 | B2: Accesso/export dati SAP disponibili con tracciato e frequenza confermati | C2: Infra | E2: Open | H2: CDG-022
A3: D2 | B3: Accesso/export Jira e Tempo disponibili con mapping utenti/progetti | C3: Infra | E3: Open | H3: CDG-023
A4: D3 | B4: Accesso CDG APP e descrizione modello dati disponibile | C4: Infra | E4: Open | H4: CDG-024
A5: D4 | B5: Prima versione tabelle di corrispondenza fornita e validata | C5: CDG | E5: Open | H5: CDG-025
A6: D5 | B6: Key user CDG disponibili per validazioni e UAT | C6: CDG | E6: Open | H6: CDG-009, CDG-028, CDG-042
A7: D6 | B7: Ambienti dev/test/prod disponibili con profili di accesso | C7: Infra | E7: Open | H7: CDG-017, CDG-021
A8: D7 | B8: Definizione soglie di quadratura e tolleranze accettate | C8: CDG | E8: Open | H8: CDG-014, CDG-032
A9: D8 | B9: Periodo campione per parallel run concordato e dati storici disponibili | C9: CDG | E9: Open | H9: CDG-043
A10: D9 | B10: Policy accesso dati HR chiarita per eventuale porting opzionale | C10: HR | E10: Open | H10: CDG-052

Sheet 03_Project_Plan
A1: # | B1: Area | C1: Attività | D1: Release | E1: Effort | F1: Owner | G1: Completion % | H1: Start Date | I1: End Date | J1: Duration | K1: Actual | L1: Task | M1: Issue Type | N1: Depends On | O1: Acceptance Criteria
A2: 1 | B2: Avvio e perimetro | C2: Kick-off progetto e allineamento stakeholder | D2: Fase 1 | E2: 1 | F2: PM | G2: 0 | J2: =IF(AND(H2<>"",I2<>""),NETWORKDAYS(H2,I2),0) -> 0 | K2: =IFERROR(E2*G2,0) -> 0 | L2: CDG-001 | M2: Task | O2: Kick-off eseguito, stakeholder e canali di governance confermati
A3: =A2+1 -> 2 | B3: Avvio e perimetro | C3: Definizione perimetro funzionale e tecnico | D3: Fase 1 | E3: 1 | F3: PM/BA | G3: 0 | J3: =IF(AND(H3<>"",I3<>""),NETWORKDAYS(H3,I3),0) -> 0 | K3: =IFERROR(E3*G3,0) -> 0 | L3: CDG-002 | M3: Story | N3: CDG-001 | O3: Perimetro condiviso e validato con business e IT
A4: =A3+1 -> 3 | B4: Avvio e perimetro | C4: Raccolta documentazione esistente e asset di progetto | D4: Fase 1 | E4: 3 | F4: BA | G4: 0 | J4: =IF(AND(H4<>"",I4<>""),NETWORKDAYS(H4,I4),0) -> 0 | K4: =IFERROR(E4*G4,0) -> 0 | L4: CDG-003 | M4: Task | N4: CDG-001 | O4: Documentazione raccolta in repository unico
A5: =A4+1 -> 4 | B5: Avvio e perimetro | C5: Impostazione piano di lavoro e governance progetto | D5: Fase 1 | E5: 2 | F5: PM | G5: 0 | J5: =IF(AND(H5<>"",I5<>""),NETWORKDAYS(H5,I5),0) -> 0 | K5: =IFERROR(E5*G5,0) -> 0 | L5: CDG-004 | M5: Task | N5: CDG-002 | O5: Piano di lavoro, meeting cadence e RAID log iniziale disponibili
A6: =A5+1 -> 5 | B6: Assessment AS-IS | C6: Analisi fonti SAP, Jira/Tempo, CDG APP e tabelle mapping | D6: Fase 1 | E6: 5 | F6: BA/TL | G6: 0 | J6: =IF(AND(H6<>"",I6<>""),NETWORKDAYS(H6,I6),0) -> 0 | K6: =IFERROR(E6*G6,0) -> 0 | L6: CDG-005 | M6: Story | N6: CDG-003 | O6: Fonti censite con owner, tracciati e modalità di accesso
A7: =A6+1 -> 6 | B7: Assessment AS-IS | C7: Mappatura flussi input grezzi e dipendenze applicative | D7: Fase 1 | E7: 5 | F7: BA | G7: 0 | J7: =IF(AND(H7<>"",I7<>""),NETWORKDAYS(H7,I7),0) -> 0 | K7: =IFERROR(E7*G7,0) -> 0 | L7: CDG-006 | M7: Task | N7: CDG-005 | O7: Flussi AS-IS disegnati e punti di controllo evidenziati
A8: =A7+1 -> 7 | B8: Assessment AS-IS | C8: Analisi qualità dati e gap principali | D8: Fase 1 | E8: 3 | F8: BA/DEV | G8: 0 | J8: =IF(AND(H8<>"",I8<>""),NETWORKDAYS(H8,I8),0) -> 0 | K8: =IFERROR(E8*G8,0) -> 0 | L8: CDG-007 | M8: Task | N8: CDG-005 | O8: Gap, anomalie ricorrenti e scarti potenziali documentati
A9: =A8+1 -> 8 | B9: Assessment AS-IS | C9: Identificazione manualità, pain point e rischi operativi | D9: Fase 1 | E9: 1 | F9: BA/PM | G9: 0 | J9: =IF(AND(H9<>"",I9<>""),NETWORKDAYS(H9,I9),0) -> 0 | K9: =IFERROR(E9*G9,0) -> 0 | L9: CDG-008 | M9: Task | N9: CDG-006 | O9: Pain point prioritizzati e validati con referenti CDG
A10: =A9+1 -> 9 | B10: Assessment AS-IS | C10: Validazione assessment AS-IS | D10: Fase 1 | E10: 1 | F10: PM/CDG | G10: 0 | J10: =IF(AND(H10<>"",I10<>""),NETWORKDAYS(H10,I10),0) -> 0 | K10: =IFERROR(E10*G10,0) -> 0 | L10: CDG-009 | M10: Milestone | N10: CDG-005, CDG-006, CDG-007, CDG-008 | O10: Verbale validazione AS-IS approvato
A11: =A10+1 -> 10 | B11: Disegno TO-BE | C11: Disegno modello dati normalizzato | D11: Fase 2 | E11: 3 | F11: TL/BA | G11: 0 | J11: =IF(AND(H11<>"",I11<>""),NETWORKDAYS(H11,I11),0) -> 0 | K11: =IFERROR(E11*G11,0) -> 0 | L11: CDG-010 | M11: Story | N11: CDG-009 | O11: Modello logico normalizzato approvato
A12: =A11+1 -> 11 | B12: Disegno TO-BE | C12: Definizione regole di normalizzazione | D12: Fase 2 | E12: 3 | F12: BA/TL | G12: 0 | J12: =IF(AND(H12<>"",I12<>""),NETWORKDAYS(H12,I12),0) -> 0 | K12: =IFERROR(E12*G12,0) -> 0 | L12: CDG-011 | M12: Story | N12: CDG-010 | O12: Regole documentate con input, output, eccezioni
A13: =A12+1 -> 12 | B13: Disegno TO-BE | C13: Definizione regole di arricchimento e ribaltamento costi | D13: Fase 2 | E13: 5 | F13: BA/CDG | G13: 0 | J13: =IF(AND(H13<>"",I13<>""),NETWORKDAYS(H13,I13),0) -> 0 | K13: =IFERROR(E13*G13,0) -> 0 | L13: CDG-012 | M13: Story | N13: CDG-010 | O13: Regole di calcolo e criteri di ribaltamento validati
A14: =A13+1 -> 13 | B14: Disegno TO-BE | C14: Definizione validità temporale mapping e storicizzazione regole | D14: Fase 2 | E14: 3 | F14: BA/TL | G14: 0 | J14: =IF(AND(H14<>"",I14<>""),NETWORKDAYS(H14,I14),0) -> 0 | K14: =IFERROR(E14*G14,0) -> 0 | L14: CDG-013 | M14: Task | N14: CDG-011 | O14: Gestione date inizio/fine validità descritta e testabile
... A55: =A54+1 -> 54 | B55: Evolutive opzionali | C55: Disegno notifiche evolute e automazioni avanzate | D55: Fase 3 | E55: 3 | F55: BA/DEV | G55: 0 | J55: =IF(AND(H55<>"",I55<>""),NETWORKDAYS(H55,I55),0) -> 0 | K55: =IFERROR(E55*G55,0) -> 0 | L55: CDG-054 | M55: Task | N55: CDG-038, CDG-053 | O55: Automazioni candidate descritte con valore e complessità

Sheet 04_Forecast
B2: 46113 | D2: Release 1 | F2: Release 2 | K2: Release 3
D3: 20 | E3: 20 | F3: 20 | G3: 20 | H3: 20 | I3: 20 | J3: 20 | K3: 20 | L3: AVG Loading
B4: Role | C4: Owner | D4: Mar | E4: Apr | F4: Mag | G4: Giu | H4: Lug | I4: Ago | J4: Set | K4: Ott
B5: PM | C5: TXT Novigo | D5: 0.5 | E5: 0.5 | F5: 0.2 | G5: 0.2 | H5: 0.2 | I5: 0.2 | J5: 0.2 | K5: 0.1 | L5: =AVERAGE(D5:K5) -> 0.2625
B6: TL | C6: TXT Novigo | D6: 0.5 | E6: 0.5 | F6: 0.25 | G6: 0 | H6: 0 | I6: 0 | J6: 0 | K6: 0 | L6: =AVERAGE(D6:K6) -> 0.15625
B7: BA | C7: TXT Novigo | D7: 0.5 | E7: 0.5 | F7: 0.25 | G7: 0.1 | H7: 0.1 | I7: 0.1 | J7: 0.1 | K7: 0 | L7: =AVERAGE(D7:K7) -> 0.20625
B8: DEV | C8: MBB | D8: 0 | E8: 0 | F8: 0 | G8: 0 | H8: 0 | I8: 0 | J8: 0 | K8: 0 | L8: =AVERAGE(D8:K8) -> 0
B9: Total | D9: =SUM(D5:D8) -> 1.5 | E9: =SUM(E5:E8) -> 1.5 | F9: =SUM(F5:F8) -> 0.7 | G9: =SUM(G5:G8) -> 0.3 | H9: =SUM(H5:H8) -> 0.3 | I9: =SUM(I5:I8) -> 0.3 | J9: =SUM(J5:J8) -> 0.3 | K9: =SUM(K5:K8) -> 0.1
B11: Role | C11: Owner | D11: Mar | E11: Apr | F11: Mag | G11: Giu | H11: Lug | I11: Ago | J11: Set | K11: Ott | L11: Total | N11: LC/HR | O11: LC /Day | P11: Costs | Q11: hr | R11: NET Day | S11: Pure Cost
B12: PM | C12: TXT Novigo | D12: =D5*D3 -> 10 | E12: =E5*E3 -> 10 | F12: =F5*F3 -> 4 | G12: =G5*G3 -> 4 | H12: =H5*H3 -> 4 | I12: =I5*I3 -> 4 | J12: =J5*J3 -> 4 | K12: =K5*K3 -> 2 | L12: =SUM(D12:K12) -> 42 | N12: =O12/8 -> 37.5 | O12: 300 | P12: =O12*L12 -> 12600 | Q12: =L12*8 -> 336 | R12: =Q12/8 -> 42 | S12: =R12*O12 -> 12600
B13: TL | C13: TXT Novigo | D13: =D6*D3 -> 10 | E13: =E6*E3 -> 10 | F13: =F6*F3 -> 5 | G13: =G6*G3 -> 0 | H13: =H6*H3 -> 0 | I13: =I6*I3 -> 0 | J13: =J6*J3 -> 0 | K13: =K6*K3 -> 0 | L13: =SUM(D13:K13) -> 25 | N13: =O13/8 -> 37.5 | O13: 300 | P13: =O13*L13 -> 7500 | Q13: =L13*8 -> 200 | R13: =Q13/8 -> 25 | S13: =R13*O13 -> 7500
B14: BA | C14: TXT Novigo | D14: =D7*D$3 -> 10 | E14: =E7*E$3 -> 10 | F14: =F7*F$3 -> 5 | G14: =G7*G$3 -> 2 | H14: =H7*H$3 -> 2 | I14: =I7*I$3 -> 2 | J14: =J7*J$3 -> 2 | K14: =K7*K$3 -> 0 | L14: =SUM(D14:K14) -> 33 | N14: =O14/8 -> 37.5 | O14: 300 | P14: =O14*L14 -> 9900 | Q14: =L14*8 -> 264 | R14: =Q14/8 -> 33 | S14: =R14*O14 -> 9900
B15: DEV | C15: MBB | D15: 34 | E15: 34 | F15: 18.5 | G15: 18.5 | H15: 18.5 | I15: 18.5 | J15: 18.5 | K15: 18.5 | L15: =SUM(D15:K15) -> 179 | N15: =O15/8 -> 38.75 | O15: 310 | P15: =O15*L15 -> 55490 | Q15: =L15*8 -> 1432 | R15: =Q15/8 -> 179 | S15: =R15*O15 -> 55490
B16: Total | D16: =SUM(D12:D15) -> 64 | E16: =SUM(E12:E15) -> 64 | F16: =SUM(F12:F15) -> 32.5 | G16: =SUM(G12:G15) -> 24.5 | H16: =SUM(H12:H15) -> 24.5 | I16: =SUM(I12:I15) -> 24.5 | J16: =SUM(J12:J15) -> 24.5 | K16: =SUM(K12:K15) -> 20.5 | L16: =SUM(L12:L15) -> 279 | P16: =SUM(P12:P15) -> 85490 | Q16: =SUM(Q12:Q15) -> 2232 | R16: =SUM(R12:R15) -> 279 | S16: =SUM(S12:S15) -> 85490
C18: AVG FTE | D18: =D16/D3 -> 3.2 | E18: =E16/E3 -> 3.2 | F18: =F16/F3 -> 1.625 | G18: =G16/G3 -> 1.225 | H18: =H16/H3 -> 1.225 | I18: =I16/I3 -> 1.225 | J18: =J16/J3 -> 1.225 | K18: =K16/K3 -> 1.025 | R18: Average Cost Rate (daily) | S18: =S16/R16 -> 306.41577
B20: Role | C20: Owner | D20: Mar | E20: Apr | F20: Mag | G20: Giu | H20: Lug | I20: Ago | J20: Set | K20: Ott
B21: PM | C21: TXT Novigo | D21: =O12*D12 -> 3000 | E21: =E12*O12 -> 3000 | F21: =F12*O12 -> 1200 | G21: =G12*O12 -> 1200 | H21: =H12*O12 -> 1200 | I21: =I12*O12 -> 1200 | J21: =J12*O12 -> 1200 | K21: =K12*O12 -> 600
B22: TL | C22: TXT Novigo | D22: =O13*D13 -> 3000 | E22: =E13*O13 -> 3000 | F22: =F13*O13 -> 1500 | G22: =G13*O13 -> 0 | H22: =H13*O13 -> 0 | I22: =I13*O13 -> 0 | J22: =J13*O13 -> 0 | K22: =K13*O13 -> 0
B23: BA | C23: TXT Novigo | D23: =O14*D14 -> 3000 | E23: =E14*O14 -> 3000 | F23: =F14*O14 -> 1500 | G23: =G14*O14 -> 600 | H23: =H14*O14 -> 600 | I23: =I14*O14 -> 600 | J23: =J14*O14 -> 600 | K23: =K14*O14 -> 0
B24: DEV | C24: MBB | D24: =O15*D15 -> 10540 | E24: =E15*O15 -> 10540 | F24: =F15*O15+30000 -> 35735 | G24: =G15*O15 -> 5735 | H24: =H15*O15 -> 5735 | I24: =I15*O15 -> 5735 | J24: =J15*O15 -> 5735 | K24: =K15*O15 -> 5735
B25: Total | D25: =SUM(D21:D24) -> 19540 | E25: =SUM(E21:E24) -> 19540 | F25: =SUM(F21:F24) -> 39935 | G25: =SUM(G21:G24) -> 7535 | H25: =SUM(H21:H24) -> 7535 | I25: =SUM(I21:I24) -> 7535 | J25: =SUM(J21:J24) -> 7535 | K25: =SUM(K21:K24) -> 6335 | L25: =SUM(D25:K25) -> 115490
B26: Contigency (%) | D26: 0 | E26: 0 | F26: 0 | G26: 0 | H26: 0 | I26: 0 | J26: 0 | K26: 1
B27: Contigency (€) | D27: =D26*'05_Risk_Assessment'!$J$13 -> 0 | E27: =E26*'05_Risk_Assessment'!$J$13 -> 0 | F27: =F26*'05_Risk_Assessment'!$J$13 -> 0 | G27: =G26*'05_Risk_Assessment'!$J$13 -> 0 | H27: =H26*'05_Risk_Assessment'!$J$13 -> 0 | I27: =I26*'05_Risk_Assessment'!$J$13 -> 0 | J27: =J26*'05_Risk_Assessment'!$J$13 -> 0 | K27: =K26*'05_Risk_Assessment'!$J$13 -> 7110 | L27: =SUM(D27:K27) -> 7110
D29: Mar | E29: Apr | F29: Mag | G29: Giu | H29: Lug | I29: Ago | J29: Set | K29: Ott
C30: Contract Value | D30: 81000 | F30: 130000
C31: EV % | D31: 0.5 | E31: 0.5 | F31: 0.2 | G31: 0.15 | H31: 0.15 | I31: 0.15 | J31: 0.15 | K31: 0.2
C32: Costs | D32: =D25+D27 -> 19540 | E32: =E25+E27 -> 19540 | F32: =F25+F27 -> 39935 | G32: =G25+G27 -> 7535 | H32: =H25+H27 -> 7535 | I32: =I25+I27 -> 7535 | J32: =J25+J27 -> 7535 | K32: =K25+K27 -> 13445 | L32: =SUM(D32:K32) -> 122600
C33: REV | D33: =$D$30*D31 -> 40500 | E33: =$D$30*E31 -> 40500 | F33: =$F$30*F31 -> 26000 | G33: =$F$30*G31 -> 19500 | H33: =$F$30*H31 -> 19500 | I33: =$F$30*I31 -> 19500 | J33: =$F$30*J31 -> 19500 | K33: =$F$30*K31 -> 26000 | L33: =SUM(D33:K33) -> 211000
C34: Margin (€) | D34: =D33-D32 -> 20960 | E34: =E33-E32 -> 20960 | F34: =F33-F32 -> -13935 | G34: =G33-G32 -> 11965 | H34: =H33-H32 -> 11965 | I34: =I33-I32 -> 11965 | J34: =J33-J32 -> 11965 | K34: =K33-K32 -> 12555 | L34: =SUM(D34:K34) -> 88400
C35: Margin (%) | D35: =IF(D33=0,"",(D33-D32)/D33) -> 0.51753086 | E35: =IF(E33=0,"",(E33-E32)/E33) -> 0.51753086 | F35: =IF(F33=0,"",(F33-F32)/F33) -> -0.53596154 | G35: =IF(G33=0,"",(G33-G32)/G33) -> 0.61358974 | H35: =IF(H33=0,"",(H33-H32)/H33) -> 0.61358974 | I35: =IF(I33=0,"",(I33-I32)/I33) -> 0.61358974 | J35: =IF(J33=0,"",(J33-J32)/J33) -> 0.61358974 | K35: =IF(K33=0,"",(K33-K32)/K33) -> 0.48288462
C36: CCI% YTD | D36: =IF(SUM($C$33:D33)=0,"",SUM($C$34:D34)/SUM($C$33:D33)) -> 0.51753086 | E36: =IF(SUM($C$33:E33)=0,"",SUM($C$34:E34)/SUM($C$33:E33)) -> 0.51753086 | F36: =IF(SUM($C$33:F33)=0,"",SUM($C$34:F34)/SUM($C$33:F33)) -> 0.26154206 | G36: =IF(SUM($C$33:G33)=0,"",SUM($C$34:G34)/SUM($C$33:G33)) -> 0.31581028 | H36: =IF(SUM($C$33:H33)=0,"",SUM($C$34:H34)/SUM($C$33:H33)) -> 0.35558219 | I36: =IF(SUM($C$33:I33)=0,"",SUM($C$34:I34)/SUM($C$33:I33)) -> 0.38598187 | J36: =IF(SUM($C$33:J33)=0,"",SUM($C$34:J34)/SUM($C$33:J33)) -> 0.40997297 | K36: =IF(SUM($C$33:K33)=0,"",SUM($C$34:K34)/SUM($C$33:K33)) -> 0.41895735 | L36: =L34/L33 -> 0.41895735

Sheet 05_Risk_Assessment
D2: RR: resource risk TR: time risk BR: business / financial risk QR: quality risk | E2: How big is the impact of the risk? 1= low 5=high | F2: How likely is the risk to occour? 1= low 5=high | G2: impact x probability Attention on risks with value of 16 and above | J2: 300
A3: No. | B3: Description of Risk | C3: Mitigation Actions | D3: Risk Category | E3: Impact | F3: Probability | G3: Overall Risk Value | H3: Impact (days extra-effort) | I3: Probabilty | J3: Contigency
A4: 1 | B4: Non completezza degli Swagger La documentazione Swagger risulta incompleta o non aggiornata, con conseguente rischio di ambiguità interpretative sulle API e possibili rallentamenti nelle attività di sviluppo e integrazione. | C4: 1)Introdurre una review formale e periodica della documentazione API (es. weekly checkpoint). 2) Definire uno standard minimo obbligatorio per gli Swagger (campi, esempi, codici errore). 3) Coinvolgere i team di sviluppo in sessioni di chiarimento anticipate (API walkthrough). 4) Utilizzare strumenti di validazione automatica degli Swagger (linting). | D4: QR | E4: 3 | F4: 3 | G4: =E4*F4 -> 9 | H4: 5 | I4: 0.6 | J4: =H4*I4*$J$2 -> 900
A5: =A4+1 -> 2 | B5: API di test non disponibili entro la data del 17/07 La mancata disponibilità delle API nell’ambiente di test entro la data prevista potrebbe compromettere la pianificazione delle attività di verifica, generando ritardi a cascata sulle fasi successive. | C5: 1) Richiedere mock API 2) Prevedere buffer temporali nel piano di test. 3) Monitorare lo stato con daily tracking e escalation rapida in caso di ritardi. | D5: TR | E5: 3 | F5: 3 | G5: =E5*F5 -> 9 | H5: 2 | I5: 0.6 | J5: =H5*I5*$J$2 -> 360
A6: =A5+1 -> 3 | B6: API non funzionanti e necessità di rework da parte di ING Il malfunzionamento delle API fornite comporta la necessità di interventi correttivi da parte di ING, con impatti su tempi, qualità complessiva della soluzione e possibile aumento delle attività di coordinamento | C6: 1)Rilascio progressivo delle API previste per anticipare la fase di test (early integration test). 2) Attivare un canale diretto di supporto tecnico 3) Documentare e tracciare i difetti con prioritizzazione condivisa. | D6: QR | E6: 5 | F6: 4 | G6: =E6*F6 -> 20 | H6: 10 | I6: 0.8 | J6: =H6*I6*$J$2 -> 2400
A7: =A6+1 -> 4 | B7: Maggiore effort per l’esecuzione dei SIT rispetto al pianificato L’esecuzione dei System Integration Test potrebbe richiedere uno sforzo superiore alle stime iniziali, a causa di complessità tecniche o dipendenze non previste, con conseguente slittamento delle tempistiche. | C7: 1) Effettuare una revisione dettagliata delle dipendenze tecniche prima dell’avvio. 2) Suddividere i test in blocchi incrementali (test per integrazione progressiva). 3) Rafforzare il team durante i SIT con risorse aggiuntive o competenze specialistiche (MBB) | D7: TR | E7: 4 | F7: 4 | G7: =E7*F7 -> 16 | H7: 5 | I7: 0.5 | J7: =H7*I7*$J$2 -> 750
A8: =A7+1 -> 5 | B8: Maggiore effort per l’esecuzione degli UAT rispetto al pianificato Le attività di User Acceptance Test potrebbero risultare più onerose del previsto, per via di un numero maggiore di casi da validare o iterazioni aggiuntive, impattando la data di go-live. | C8: 1) Definire casi di test prioritari (risk-based testing). 2) Coinvolgere gli utenti business in fasi preliminari di validazione. 3) Preparare ambienti e dati di test realistici in anticipo. 4) Pianificare slot dedicati e vincolanti per gli utenti UAT. | D8: TR | E8: 4 | F8: 4 | G8: =E8*F8 -> 16 | H8: 5 | I8: 0.5 | J8: =H8*I8*$J$2 -> 750
A9: =A8+1 -> 6 | B9: Necessità di maggiore effort per l’analisi di dettaglio La fase di analisi potrebbe richiedere un approfondimento superiore alle attese per chiarire requisiti incompleti o evolutivi, con impatti su tempi e allocazione delle risorse progettuali. | C9: 1) Organizzare workshop di approfondimento funzionale con stakeholder chiave. 2) Formalizzare i requisiti tramite condivisione e validazione 2) Applicare un approccio iterativo (es. refinement continuo). | D9: BR | E9: 4 | F9: 4 | G9: =E9*F9 -> 16 | H9: 10 | I9: 0.5 | J9: =H9*I9*$J$2 -> 1500
A10: =A9+1 -> 7 | B10: Necessità di maggiori risorse per il supporto Il livello di supporto richiesto potrebbe eccedere quanto pianificato, rendendo necessaria l’allocazione di risorse aggiuntive per garantire continuità operativa e qualità del servizio | C10: 1) Creare una knowledge base all'interno del materiale di formazione per ridurre richieste ripetitive. 2) Pianificare capacity buffer o risorse on-demand. | D10: RR | E10: 3 | F10: 3 | G10: =E10*F10 -> 9 | H10: 5 | I10: 0.3 | J10: =H10*I10*$J$2 -> 450
H13: =J13/J2 -> 23.7 | J13: =SUM(J4:J10) -> 7110
A15: Risk Category | B15: Sum of Overall Risk Value
A16: BR | B16: 16
A17: QR | B17: 29
A18: RR | B18: 9
A19: TR | B19: 41
A20: Grand Total | B20: 95

Sheet Totali per area
A3: Etichette di riga | B3: Somma di Effort
A4: Assessment AS-IS | B4: 15
A5: Avvio e perimetro | B5: 7 | M5: =84*2 -> 168 | N5: =M5/15 -> 11.2
A6: Dashboard e Output | B6: 19 | M6: 13 | N6: =M6*N5 -> 145.6
A7: Disegno TO-BE | B7: 19
A8: Elaborazioni | B8: 22
A9: Evolutive opzionali | B9: 11
A10: Go live e hypercare | B10: 13
A11: Normalizzazione | B11: 27
A12: Setup Ambienti | B12: 13
A13: Test e parallel run | B13: 19
A14: Totale complessivo | B14: 165 | F14: =GETPIVOTDATA("Effort",$A$3)/20 -> 8.25
A17: =15/5 -> 3
